mcp_applescript/__init__.py
mcp_applescript/utils.py
mcp_applescript-0.1.3.dist-info/WHEEL
mcp_applescript-0.1.3.dist-info/entry_points.txt
mcp_applescript-0.1.3.dist-info/METADATA
mcp_applescript-0.1.3.dist-info/RECORD
