Metadata-Version: 2.3
Name: mcp-applescript
Version: 0.1.3
Summary: An MCP server that enables LLMs to execute AppleScript commands on macOS
Keywords: mcp,llm,applescript,macos,automation
Author: Paul-Louis Pröve
Author-email: Paul-Louis Pröve <plp@workgenius.com>
License: MIT
Classifier: Development Status :: 3 - Alpha
Classifier: Intended Audience :: Developers
Classifier: License :: OSI Approved :: MIT License
Classifier: Programming Language :: Python :: 3
Classifier: Programming Language :: Python :: 3.12
Classifier: Topic :: Software Development :: Libraries :: Python Modules
Classifier: Operating System :: MacOS
Requires-Dist: mcp>=1.13.1
Requires-Python: >=3.12
Project-URL: Homepage, https://github.com/pietz/mcp-applescript
Project-URL: Issues, https://github.com/pietz/mcp-applescript/issues
